{"nofootprint":[5],"noatime":[27],"non":[14,23,24,25,26,34,37,38,45],"novell":[12],"notmatch":[26],"nouser":[27],"node":[39],"nonblank":[45],"nodes":[2,6],"no":[7,9,18,24,26,35,38,40,47,49,50,53,55],"notifications":[9],"normal":[10,14,15,19,26,34,35,49,53,55],"noop":[16],"nohup":[39],"now":[26],"note":[24,25,32,38],"not":[12,24,26,34,40,51,54],"notlike":[26],"notepad":[26,35],"nospace":[40],"nofail":[27],"notification":[32],"notify":[9],"notice":[6],"nonewwindow":[26],"november":[12],"notes":[0,1,2,9,30,35],"notcontains":[26],"notin":[26]}