{"standards":[2,15,23,47],"stick":[41],"store":[2,15,47,49],"steve":[25],"step":[5,21,32,42,49],"studies":[1],"stars":[19],"std":[29],"standalone":[15],"strings":[11,17,20,27,38,39],"stacking":[33],"stdout":[2,19,27,34,38,45],"students":[13],"styles":[22,51,54],"structures":[2,7,27,47],"statement":[27,35],"streaming":[33],"sticky":[34,47],"starting":[39,45,50],"stopping":[38],"standardize":[13],"startup":[14,19,22,23,30],"streamreader":[27],"styling":[7,24,44],"steps":[5,29],"stream":[2,25,27,38],"student":[13],"stashes":[0],"structured":[10,27,47],"string":[8,18,26,27,34,38,39,44,54],"stallman":[13,36],"stdin":[2,20,34,38,53],"strictly":[16,21,23],"stable":[21,27],"styled":[0,2],"study":[2,9],"stashing":[4],"structural":[22,36],"still":[27],"storage":[0,7,14,26,28,33,36,47],"stopped":[17],"streams":[0,27,38],"stackable":[33],"statically":[2],"stylesheet":[5],"strict":[23,35,36],"status":[4,7,17,26,30,31,35,38,39,52],"structure":[2,5,15,18,22,23,24,27,28,29,35,38,39,45,48],"stashed":[4],"style":[2,5,13,14,16,27,35,36,37,39,52],"steep":[36],"states":[7],"stand":[10],"stderr":[19,34,38],"stash":[4],"string1":[27],"stop":[2],"sthapna":[13],"string2":[27],"start":[2,11,18,27,30,35,36,39,40,47,53],"standard":[2,3,5,6,7,8,12,16,18,19,20,22,24,25,26,27,28,29,30,32,34,35,36,38,39,40,44,46,47,53],"static":[0,2,5,27,28,32,41],"state":[2,4,7,13,14,15,27,28],"started":[0,1,5,18],"structs":[8],"stats":[18]}